airports/__init__.py
airports/admin.py
airports/apps.py
airports/conf.py
airports/models.py
airports/management/__init__.py
airports/management/commands/__init__.py
airports/management/commands/airports.py
airports/migrations/0001_initial.py
airports/migrations/__init__.py
airports/static/css/airports.css
airports/static/js/airports.js
airports/templates/airports/base.html
django_airports_legacy-0.2.6.dist-info/AUTHORS.rst
django_airports_legacy-0.2.6.dist-info/LICENSE
django_airports_legacy-0.2.6.dist-info/METADATA
django_airports_legacy-0.2.6.dist-info/WHEEL
django_airports_legacy-0.2.6.dist-info/top_level.txt
django_airports_legacy-0.2.6.dist-info/RECORD
