Metadata-Version: 2.1
Name: django-airports-legacy
Version: 0.2.6
Summary: It's like django-cities, but django-airports 
Home-page: https://github.com/vlinhart/django-airports-legacy
Author: Antonio Ercole De Luca
Author-email: eracle@posteo.eu
License: MIT
Keywords: django-airports-legacy
Platform: UNKNOWN
Classifier: Development Status :: 3 - Alpha
Classifier: Framework :: Django
Classifier: Framework :: Django :: 2.0
Classifier: Intended Audience :: Developers
Classifier: License :: OSI Approved :: BSD License
Classifier: Natural Language :: English
Classifier: Programming Language :: Python :: 2
Classifier: Programming Language :: Python :: 2.7
Classifier: Programming Language :: Python :: 3
Classifier: Programming Language :: Python :: 3.4
Classifier: Programming Language :: Python :: 3.5
Classifier: Programming Language :: Python :: 3.6
Classifier: Programming Language :: Python :: 3.7
Classifier: Programming Language :: Python :: 3.8
License-File: LICENSE
License-File: AUTHORS.rst
Requires-Dist: django-model-utils (>=2.0)
Requires-Dist: django-cities-legacy (>=0.6.2)
